pygifconvt_m/__init__.py
pygifconvt_m/converter.py
pygifconvt_m-1.0.0.dist-info/LICENSE
pygifconvt_m-1.0.0.dist-info/METADATA
pygifconvt_m-1.0.0.dist-info/WHEEL
pygifconvt_m-1.0.0.dist-info/top_level.txt
pygifconvt_m-1.0.0.dist-info/RECORD
