Metadata-Version: 2.1
Name: pygifconvt-m
Version: 1.0.0
Summary: Test package for distribution
Home-page: UNKNOWN
Author: motive
Author-email: kdg_1016@naver.com
License: UNKNOWN
Keywords: GIFCONVERTER,gifconverter
Platform: UNKNOWN
Classifier: Programming Language :: Python :: 3
Classifier: License :: OSI Approved :: MIT License
Classifier: Operating System :: OS Independent
Requires-Python: >=3
Requires-Dist: pillow
